sept/__init__.py
sept/_version.py
sept/balancer.py
sept/documentation.py
sept/errors.py
sept/operator.py
sept/operator_manager.py
sept/parser.py
sept/template.py
sept/template_tokenizer.py
sept/token.py
sept/token_manager.py
sept/builtin/__init__.py
sept/builtin/operators/__init__.py
sept/builtin/operators/lower.py
sept/builtin/operators/null.py
sept/builtin/operators/pad.py
sept/builtin/operators/replace.py
sept/builtin/operators/substr.py
sept/builtin/operators/upper.py
sept/builtin/tokens/__init__.py
sept/builtin/tokens/default.py
sept-0.4.2.dist-info/LICENSE.txt
sept-0.4.2.dist-info/METADATA
sept-0.4.2.dist-info/WHEEL
sept-0.4.2.dist-info/top_level.txt
sept-0.4.2.dist-info/RECORD
